pupil_pthreads_win/__init__.py
pupil_pthreads_win/data/COPYING
pupil_pthreads_win/data/COPYING.LIB
pupil_pthreads_win/data/include/pthread.h
pupil_pthreads_win/data/include/sched.h
pupil_pthreads_win/data/include/semaphore.h
pupil_pthreads_win/data/lib/x64/pthreadVC2.dll
pupil_pthreads_win/data/lib/x64/pthreadVC2.lib
pupil_pthreads_win-2.dist-info/LICENSE.md
pupil_pthreads_win-2.dist-info/METADATA
pupil_pthreads_win-2.dist-info/WHEEL
pupil_pthreads_win-2.dist-info/top_level.txt
pupil_pthreads_win-2.dist-info/RECORD
