Metadata-Version: 2.1
Name: pupil-pthreads-win
Version: 2
Summary: A precompiled version of pthreads-win.
Home-page: https://github.com/pupil-labs/pupil-pthreads-win
Author: Pupil Labs GmbH
Author-email: pypi@pupil-labs.com
License: MIT License
Platform: UNKNOWN
Classifier: Development Status :: 2 - Pre-Alpha
Classifier: Intended Audience :: Developers
Classifier: License :: OSI Approved :: MIT License
Classifier: Natural Language :: English
Classifier: Programming Language :: Python :: 3.6
Classifier: Programming Language :: Python :: 3.7
